{
  "generatedAt": "2026-07-09T13:39:00.364Z",
  "schedule": "*/10 * * * *",
  "services": {
    "oxgn-csa": {
      "lastPingAt": "2026-07-09T13:39:00.186Z",
      "ok": true,
      "statusCode": 200,
      "latencyMs": 208,
      "error": null,
      "totalPings": 197,
      "consecutiveFailures": 0
    },
    "oxgn-csa-api": {
      "lastPingAt": "2026-07-09T13:39:00.364Z",
      "ok": true,
      "statusCode": 200,
      "latencyMs": 177,
      "error": null,
      "totalPings": 196,
      "consecutiveFailures": 0
    }
  }
}
