{
  "generatedAt": "2026-07-18T19:36:13.909Z",
  "schedule": "*/10 * * * *",
  "services": {
    "oxgn-csa": {
      "lastPingAt": "2026-07-18T19:36:13.785Z",
      "ok": false,
      "statusCode": 503,
      "latencyMs": 147,
      "error": "HTTP 503",
      "totalPings": 328,
      "consecutiveFailures": 91
    },
    "oxgn-csa-api": {
      "lastPingAt": "2026-07-18T19:36:13.909Z",
      "ok": false,
      "statusCode": 503,
      "latencyMs": 123,
      "error": "HTTP 503",
      "totalPings": 327,
      "consecutiveFailures": 91
    }
  }
}
