{
  "generatedAt": "2026-07-23T17:51:15.732Z",
  "schedule": "*/10 * * * *",
  "services": {
    "oxgn-csa": {
      "lastPingAt": "2026-07-23T17:51:15.549Z",
      "ok": false,
      "statusCode": 503,
      "latencyMs": 354,
      "error": "HTTP 503",
      "totalPings": 394,
      "consecutiveFailures": 157
    },
    "oxgn-csa-api": {
      "lastPingAt": "2026-07-23T17:51:15.731Z",
      "ok": false,
      "statusCode": 503,
      "latencyMs": 181,
      "error": "HTTP 503",
      "totalPings": 393,
      "consecutiveFailures": 157
    }
  }
}
