{
  "generatedAt": "2026-07-06T20:20:39.204Z",
  "schedule": "*/10 * * * *",
  "services": {
    "oxgn-csa": {
      "lastPingAt": "2026-07-06T20:20:38.895Z",
      "ok": true,
      "statusCode": 200,
      "latencyMs": 320,
      "error": null,
      "totalPings": 168,
      "consecutiveFailures": 0
    },
    "oxgn-csa-api": {
      "lastPingAt": "2026-07-06T20:20:39.204Z",
      "ok": true,
      "statusCode": 200,
      "latencyMs": 306,
      "error": null,
      "totalPings": 167,
      "consecutiveFailures": 0
    }
  }
}
