{
  "generatedAt": "2026-07-08T23:54:46.540Z",
  "schedule": "*/10 * * * *",
  "services": {
    "oxgn-csa": {
      "lastPingAt": "2026-07-08T23:54:46.453Z",
      "ok": true,
      "statusCode": 200,
      "latencyMs": 183,
      "error": null,
      "totalPings": 193,
      "consecutiveFailures": 0
    },
    "oxgn-csa-api": {
      "lastPingAt": "2026-07-08T23:54:46.540Z",
      "ok": true,
      "statusCode": 200,
      "latencyMs": 86,
      "error": null,
      "totalPings": 192,
      "consecutiveFailures": 0
    }
  }
}
