{
  "generatedAt": "2026-07-02T06:06:05.168Z",
  "schedule": "*/10 * * * *",
  "services": {
    "oxgn-csa": {
      "lastPingAt": "2026-07-02T06:06:04.977Z",
      "ok": true,
      "statusCode": 200,
      "latencyMs": 290,
      "error": null,
      "totalPings": 113,
      "consecutiveFailures": 0
    },
    "oxgn-csa-api": {
      "lastPingAt": "2026-07-02T06:06:05.168Z",
      "ok": true,
      "statusCode": 200,
      "latencyMs": 189,
      "error": null,
      "totalPings": 112,
      "consecutiveFailures": 0
    }
  }
}
