{
  "generatedAt": "2026-07-12T01:12:13.322Z",
  "schedule": "*/10 * * * *",
  "services": {
    "oxgn-csa": {
      "lastPingAt": "2026-07-12T01:12:13.175Z",
      "ok": true,
      "statusCode": 200,
      "latencyMs": 209,
      "error": null,
      "totalPings": 231,
      "consecutiveFailures": 0
    },
    "oxgn-csa-api": {
      "lastPingAt": "2026-07-12T01:12:13.322Z",
      "ok": true,
      "statusCode": 200,
      "latencyMs": 146,
      "error": null,
      "totalPings": 230,
      "consecutiveFailures": 0
    }
  }
}
