{
  "generatedAt": "2026-07-02T18:15:57.016Z",
  "schedule": "*/10 * * * *",
  "services": {
    "oxgn-csa": {
      "lastPingAt": "2026-07-02T18:15:56.855Z",
      "ok": true,
      "statusCode": 200,
      "latencyMs": 324,
      "error": null,
      "totalPings": 118,
      "consecutiveFailures": 0
    },
    "oxgn-csa-api": {
      "lastPingAt": "2026-07-02T18:15:57.016Z",
      "ok": true,
      "statusCode": 200,
      "latencyMs": 159,
      "error": null,
      "totalPings": 117,
      "consecutiveFailures": 0
    }
  }
}
